pyseaweed/__init__.py
pyseaweed/exceptions.py
pyseaweed/func_tests.py
pyseaweed/tests.py
pyseaweed/utils.py
pyseaweed/version.py
pyseaweed/weed.py
pyseaweed-1.0.2.dist-info/DESCRIPTION.rst
pyseaweed-1.0.2.dist-info/METADATA
pyseaweed-1.0.2.dist-info/RECORD
pyseaweed-1.0.2.dist-info/WHEEL
pyseaweed-1.0.2.dist-info/metadata.json
pyseaweed-1.0.2.dist-info/top_level.txt
