Metadata-Version: 2.0
Name: pyseaweed
Version: 1.0.2
Summary: Module to simplify usage of WeedFS in python.
Home-page: https://github.com/utek/pyseaweed
Author: Łukasz Bołdys
Author-email: mail@utek.pl
License: Copyright (C) 2014 Lukasz Boldys
Requires-Dist: requests
Requires-Dist: six
